aipysdk/__init__.py
aipysdk-0.0.1.dist-info/METADATA
aipysdk-0.0.1.dist-info/WHEEL
aipysdk-0.0.1.dist-info/RECORD
